set_nested_iters/LICENSE
set_nested_iters/README.MD
set_nested_iters/__init__.py
set_nested_iters/requirements.txt
set_nested_iters/thirdparty.json
set_nested_iters-0.10.dist-info/LICENSE.rst
set_nested_iters-0.10.dist-info/METADATA
set_nested_iters-0.10.dist-info/WHEEL
set_nested_iters-0.10.dist-info/top_level.txt
set_nested_iters-0.10.dist-info/RECORD
